monarch_converter.py
monarch_converter-0.1.0.dist-info/licenses/LICENSE
monarch_converter-0.1.0.dist-info/METADATA
monarch_converter-0.1.0.dist-info/WHEEL
monarch_converter-0.1.0.dist-info/entry_points.txt
monarch_converter-0.1.0.dist-info/top_level.txt
monarch_converter-0.1.0.dist-info/RECORD
