Metadata-Version: 2.4
Name: monarch-converter
Version: 0.1.0
Summary: Translate Mint.com csv's for Monarch Money Import
Project-URL: Homepage, https://github.com/rveachkc/monarch-converter
Requires-Python: >=3.12
License-File: LICENSE
Requires-Dist: polars>=1.32.0
Requires-Dist: polars-lts-cpu>=1.32.0
Requires-Dist: python-slugify>=8.0.4
Dynamic: license-file
